mykad/__init__.py
mykad/constants.py
mykad/mykad.py
mykad/utils.py
mykad-0.3.0.dist-info/LICENSE
mykad-0.3.0.dist-info/METADATA
mykad-0.3.0.dist-info/WHEEL
mykad-0.3.0.dist-info/top_level.txt
mykad-0.3.0.dist-info/RECORD
