Metadata-Version: 2.1
Name: mykad
Version: 0.3.0
Summary: A Python package to validate MyKad numbers
Home-page: https://github.com/pongloongyeat/mykad
Author: Pong Loong Yeat
Author-email: pongloongyeat@gmail.com
License: UNKNOWN
Project-URL: Bug Tracker, https://github.com/pongloongyeat/mykad/issues
Platform: UNKNOWN
Classifier: Programming Language :: Python :: 3
Classifier: License :: OSI Approved :: MIT License
Classifier: Operating System :: OS Independent
Requires-Python: >=3.6
License-File: LICENSE
